flask_honeyauth.py
Flask_HoneyAuth-1.1.0.dist-info/AUTHORS
Flask_HoneyAuth-1.1.0.dist-info/LICENSE
Flask_HoneyAuth-1.1.0.dist-info/METADATA
Flask_HoneyAuth-1.1.0.dist-info/WHEEL
Flask_HoneyAuth-1.1.0.dist-info/top_level.txt
Flask_HoneyAuth-1.1.0.dist-info/RECORD
